setup.py
coreinit/__init__.py
coreinit/settings.py
coreinit.egg-info/PKG-INFO
coreinit.egg-info/SOURCES.txt
coreinit.egg-info/dependency_links.txt
coreinit.egg-info/top_level.txt
coreinit/db/__init__.py
coreinit/db/model.py
coreinit/db/drivers/__init__.py
coreinit/db/drivers/cache_interface.py
coreinit/db/drivers/redis_driver.py
coreinit/logger/__init__.py
coreinit/logger/logger_base.py
coreinit/logger/syslog_driver.py
coreinit/mgmt/__init__.py
coreinit/mgmt/mgmt_base.py
coreinit/msg/__init__.py
coreinit/msg/queue_base.py
coreinit/msg/queue_socket.py
coreinit/msg/queue_zmq.py
coreinit/service/__init__.py
coreinit/service/service_base.py
coreinit/service/mixins/__init__.py
coreinit/service/mixins/avahi.py
coreinit/service/mixins/daemon.py
coreinit/utils/__init__.py
coreinit/utils/exceptions.py
coreinit/utils/installer.py
coreinit/utils/template.py