Metadata-Version: 1.1
Name: coreinit
Version: 15.11.18
Summary: Service autodeploy and autoconfig library
Home-page: http://cloudover.org/coreinit/
Author: Marta Nabozny
Author-email: martastrzet@gmail.com
License: UNKNOWN
Download-URL: https://github.com/cloudOver/CoreInit/archive/master.zip
Keywords: overcluster,cloudover,cloud
Platform: UNKNOWN
